vn100/__init__.py
vn100/cksm.py
vn100/config.py
vn100/controller.py
vn100/interface_server.py
vn100/iusd.py
vn100/udp_server.py
vn100/vn100_modules/__init__.py
vn100/vn100_modules/async_serial.py
vn100/vn100_modules/attitude.py
vn100/vn100_modules/driver_db.py
vn100/vn100_modules/health_watchdog.py
vn100/vn100_modules/hsie.py
vn100/vn100_modules/imu.py
vn100/vn100_modules/parser.py
vn100/vn100_modules/register_manager.py
vn100/vn100_modules/system.py
vn100/vn100_modules/vel_aiding.py
vn100/vn100_modules/world_mag_grav.py
vn100/vn100_modules/logger/__init__.py
vn100/vn100_modules/logger/create_log.py
vn100/vn100_modules/resources/__init__.py
vn100/vn100_modules/resources/mod_16bit_crc.py
vn100/vn100_modules/resources/mod_8bit_cksm.py
vn100_inm_pt-0.12.dist-info/LICENSE
vn100_inm_pt-0.12.dist-info/METADATA
vn100_inm_pt-0.12.dist-info/WHEEL
vn100_inm_pt-0.12.dist-info/top_level.txt
vn100_inm_pt-0.12.dist-info/RECORD
