Metadata-Version: 2.1
Name: vn100-inm-pt
Version: 0.12
Summary: VectorNav VN-100 INM interface server
Home-page: https://github.com/palcort-tech/internal-vn100
Author: Palcort Tech S.A.S.
Author-email: info@palcort.com
License: UNKNOWN
Platform: UNKNOWN
Classifier: Programming Language :: Python :: 3
Classifier: License :: OSI Approved :: MIT License
Classifier: Operating System :: OS Independent
Requires-Python: >=3.6
License-File: LICENSE
Requires-Dist: pyserial (<=3.4)
